janggi/__init__.py
janggi/constants.py
janggi/main.py
janggi/utils.py
janggi/base/__init__.py
janggi/base/board.py
janggi/base/camp.py
janggi/base/formation.py
janggi/base/location.py
janggi/base/move.py
janggi/base/piece.py
janggi/game/__init__.py
janggi/game/game_log.py
janggi/game/janggi_game.py
janggi/proto/__init__.py
janggi/proto/log_pb2.py
janggi/ui/__init__.py
janggi/ui/game_player.py
janggi/ui/game_window.py
janggi/ui/marker.py
janggi/ui/replay_viewer.py
janggi/ui/images/board.png
janggi/ui/images/cho_cannon.png
janggi/ui/images/cho_chariot.png
janggi/ui/images/cho_elephant.png
janggi/ui/images/cho_general.png
janggi/ui/images/cho_guard.png
janggi/ui/images/cho_horse.png
janggi/ui/images/cho_soldier.png
janggi/ui/images/han_cannon.png
janggi/ui/images/han_chariot.png
janggi/ui/images/han_elephant.png
janggi/ui/images/han_general.png
janggi/ui/images/han_guard.png
janggi/ui/images/han_horse.png
janggi/ui/images/han_soldier.png
janggi-1.0.5.dist-info/LICENSE
janggi-1.0.5.dist-info/METADATA
janggi-1.0.5.dist-info/WHEEL
janggi-1.0.5.dist-info/top_level.txt
janggi-1.0.5.dist-info/RECORD
