Metadata-Version: 2.1
Name: janggi
Version: 1.0.5
Summary: Python library for Korean chess Janggi
Home-page: https://github.com/sungho-cho/pyjanggi
Author: Sungho Cho
Author-email: didog9595@gmail.com
Classifier: Programming Language :: Python :: 3
Classifier: License :: OSI Approved :: MIT License
Classifier: Operating System :: OS Independent
Requires-Python: >=3.6
License-File: LICENSE
Requires-Dist: termcolor (==1.1.0)
Requires-Dist: pygame (==2.1.2)
